ploy_fabric/__init__.py
ploy_fabric/_fabric_integration.py
ploy_fabric/test_fabric.py
ploy_fabric-2.0.0.dist-info/LICENSE.txt
ploy_fabric-2.0.0.dist-info/METADATA
ploy_fabric-2.0.0.dist-info/WHEEL
ploy_fabric-2.0.0.dist-info/entry_points.txt
ploy_fabric-2.0.0.dist-info/top_level.txt
ploy_fabric-2.0.0.dist-info/RECORD
