Metadata-Version: 2.1
Name: ploy-fabric
Version: 2.0.0
Summary: Plugin to integrate Fabric with ploy.
Home-page: http://github.com/ployground/ploy_fabric
Author: Florian Schulze
Author-email: florian.schulze@gmx.net
License: BSD 3-Clause License
Platform: UNKNOWN
Classifier: Environment :: Console
Classifier: Intended Audience :: System Administrators
Classifier: Programming Language :: Python :: 2.7
Classifier: Programming Language :: Python :: 3.7
Classifier: Programming Language :: Python :: 3.8
Classifier: Programming Language :: Python :: 3.9
Classifier: Programming Language :: Python :: 3.10
Classifier: Topic :: System :: Installation/Setup
Classifier: Topic :: System :: Systems Administration
Requires-Python: >=2.7, !=3.0.*, !=3.1.*, !=3.2.*, !=3.3.*, !=3.4.*, !=3.5.*, !=3.6.*
License-File: LICENSE.txt
Requires-Dist: setuptools
Requires-Dist: ploy (>=2.0.0)
Requires-Dist: Fabric (!=1.8.3,<2dev,>=1.4.0)
